snparcher/__init__.py
snparcher/utils.py
snparcher/cli/__init__.py
snparcher/snk_config/main.yaml
snparcher/snk_config/qc.yaml
snparcher/workflow/Snakefile
snparcher/workflow/envs/angsd.yml
snparcher/workflow/envs/bam2vcf.yml
snparcher/workflow/envs/bcftools.yml
snparcher/workflow/envs/cov_filter.yml
snparcher/workflow/envs/fastq2bam.yml
snparcher/workflow/envs/mappability.yml
snparcher/workflow/envs/sambamba.yml
snparcher/workflow/envs/sentieon.yml
snparcher/workflow/envs/ucsc.yml
snparcher/workflow/modules/qc/Snakefile
snparcher/workflow/modules/qc/common.smk
snparcher/workflow/modules/qc/config/config.bak..yaml
snparcher/workflow/modules/qc/config/test.csv
snparcher/workflow/modules/qc/config/test_coords.csv
snparcher/workflow/modules/qc/envs/admixture.yml
snparcher/workflow/modules/qc/envs/plink.yml
snparcher/workflow/modules/qc/envs/qc.yml
snparcher/workflow/modules/qc/envs/subsample_snps.yml
snparcher/workflow/modules/qc/envs/vcftools_individuals.yml
snparcher/workflow/modules/qc/scripts/contigs4admixture.py
snparcher/workflow/modules/qc/scripts/qc_dashboard_interactive.Rmd
snparcher/workflow/modules/qc/scripts/qc_dashboard_render.R
snparcher/workflow/rules/alignment.smk
snparcher/workflow/rules/common.smk
snparcher/workflow/rules/fastq.smk
snparcher/workflow/rules/gatk_hc_intervals.smk
snparcher/workflow/rules/intervals.smk
snparcher/workflow/rules/preflight.smk
snparcher/workflow/rules/reference.smk
snparcher-0.1.0.dist-info/METADATA
snparcher-0.1.0.dist-info/WHEEL
snparcher-0.1.0.dist-info/entry_points.txt
snparcher-0.1.0.dist-info/RECORD
