Metadata-Version: 2.3
Name: snparcher
Version: 0.1.0
Summary: Add your description here
Requires-Python: >=3.12
Requires-Dist: cyvcf2>=0.31.1
Requires-Dist: pandas>=2.2.2
Requires-Dist: pandera>=0.21.0
Requires-Dist: pytest-workflow>=2.1.0
Requires-Dist: snk-cli>=0.5.5
